matrixbuffer/Graphics.py
matrixbuffer/MatrixBuffer.py
matrixbuffer/__init__.py
matrixbuffer-0.2.9.dist-info/licenses/LICENSE
matrixbuffer-0.2.9.dist-info/METADATA
matrixbuffer-0.2.9.dist-info/WHEEL
matrixbuffer-0.2.9.dist-info/top_level.txt
matrixbuffer-0.2.9.dist-info/RECORD
